setup.py
model/__init__.py
model/cookbook.py
model/product.py
model/product_package.py
package_generator.egg-info/PKG-INFO
package_generator.egg-info/SOURCES.txt
package_generator.egg-info/dependency_links.txt
package_generator.egg-info/requires.txt
package_generator.egg-info/top_level.txt
tests/__init__.py
tests/acceptance/__init__.py
tests/acceptance/test_deploy_packages.py
tests/unit/__init__.py
tests/unit/test_cookbook.py
tests/unit/test_product.py
tests/unit/test_product_package.py
util/__init__.py
util/configuration.py
util/osclients.py
util/utils_clients.py
util/utils_file.py