Metadata-Version: 1.0
Name: package-generator
Version: 0.0.1
Summary: Package Generator
Home-page: https://github.com/telefonicaid/fiware-enablers/package-generator
Author: UNKNOWN
Author-email: UNKNOWN
License: UNKNOWN
Platform: UNKNOWN
